{
  "id": "zm-act-si-2018-94",
  "type": "statute",
  "title": "Electoral Process (Local Governments By-Elections) (Election Date and Time of Poll) (No. 7) Order, 2018",
  "title_en": "Electoral Process (Local Governments By-Elections) (Election Date and Time of Poll) (No. 7) Order, 2018",
  "short_name": "Electoral Process (Local Go...",
  "status": "in_force",
  "issued_date": "",
  "in_force_date": "",
  "url": "https://zambialii.org/akn/zm/act/si/2018/94/eng@2018-12-21",
  "provisions": [],
  "definitions": []
}